construct_hub/__init__.py
construct_hub/py.typed
construct_hub/_jsii/__init__.py
construct_hub/_jsii/construct-hub@0.3.271.jsii.tgz
construct_hub/sources/__init__.py
construct_hub-0.3.271.dist-info/LICENSE
construct_hub-0.3.271.dist-info/METADATA
construct_hub-0.3.271.dist-info/NOTICE
construct_hub-0.3.271.dist-info/WHEEL
construct_hub-0.3.271.dist-info/top_level.txt
construct_hub-0.3.271.dist-info/RECORD
