Metadata-Version: 2.1
Name: construct-hub
Version: 0.3.271
Summary: A construct library that models Construct Hub instances.
Home-page: https://github.com/cdklabs
Author: Amazon Web Services, Inc.<construct-ecosystem-team@amazon.com>
License: Apache-2.0
Project-URL: Source, https://github.com/cdklabs/construct-hub.git
Platform: UNKNOWN
Classifier: Intended Audience :: Developers
Classifier: Operating System :: OS Independent
Classifier: Programming Language :: JavaScript
Classifier: Programming Language :: Python :: 3 :: Only
Classifier: Programming Language :: Python :: 3.6
Classifier: Programming Language :: Python :: 3.7
Classifier: Programming Language :: Python :: 3.8
Classifier: Programming Language :: Python :: 3.9
Classifier: Typing :: Typed
Classifier: Development Status :: 4 - Beta
Classifier: License :: OSI Approved
Requires-Python: >=3.6
License-File: LICENSE
License-File: NOTICE
Requires-Dist: aws-cdk.assets (<2.0.0,>=1.128.0)
Requires-Dist: aws-cdk.aws-certificatemanager (<2.0.0,>=1.128.0)
Requires-Dist: aws-cdk.aws-cloudfront-origins (<2.0.0,>=1.128.0)
Requires-Dist: aws-cdk.aws-cloudfront (<2.0.0,>=1.128.0)
Requires-Dist: aws-cdk.aws-cloudwatch-actions (<2.0.0,>=1.128.0)
Requires-Dist: aws-cdk.aws-cloudwatch (<2.0.0,>=1.128.0)
Requires-Dist: aws-cdk.aws-codeartifact (<2.0.0,>=1.128.0)
Requires-Dist: aws-cdk.aws-ec2 (<2.0.0,>=1.128.0)
Requires-Dist: aws-cdk.aws-ecs (<2.0.0,>=1.128.0)
Requires-Dist: aws-cdk.aws-events-targets (<2.0.0,>=1.128.0)
Requires-Dist: aws-cdk.aws-events (<2.0.0,>=1.128.0)
Requires-Dist: aws-cdk.aws-iam (<2.0.0,>=1.128.0)
Requires-Dist: aws-cdk.aws-lambda-event-sources (<2.0.0,>=1.128.0)
Requires-Dist: aws-cdk.aws-lambda (<2.0.0,>=1.128.0)
Requires-Dist: aws-cdk.aws-logs (<2.0.0,>=1.128.0)
Requires-Dist: aws-cdk.aws-route53-targets (<2.0.0,>=1.128.0)
Requires-Dist: aws-cdk.aws-route53 (<2.0.0,>=1.128.0)
Requires-Dist: aws-cdk.aws-s3-deployment (<2.0.0,>=1.128.0)
Requires-Dist: aws-cdk.aws-s3-notifications (<2.0.0,>=1.128.0)
Requires-Dist: aws-cdk.aws-s3 (<2.0.0,>=1.128.0)
Requires-Dist: aws-cdk.aws-sns (<2.0.0,>=1.128.0)
Requires-Dist: aws-cdk.aws-sqs (<2.0.0,>=1.128.0)
Requires-Dist: aws-cdk.aws-stepfunctions-tasks (<2.0.0,>=1.128.0)
Requires-Dist: aws-cdk.aws-stepfunctions (<2.0.0,>=1.128.0)
Requires-Dist: aws-cdk.core (<2.0.0,>=1.128.0)
Requires-Dist: aws-cdk.custom-resources (<2.0.0,>=1.128.0)
Requires-Dist: aws-cdk.cx-api (<2.0.0,>=1.128.0)
Requires-Dist: cdk-watchful (<0.6.0,>=0.5.196)
Requires-Dist: constructs (<4.0.0,>=3.3.69)
Requires-Dist: jsii (<2.0.0,>=1.55.0)
Requires-Dist: publication (>=0.0.3)
